mmkg_vrd/__init__.py
mmkg_vrd/install.txt
mmkg_vrd/models.py
mmkg_vrd/maskrcnn_benchmark/_C.cpython-37m-x86_64-linux-gnu.so
mmkg_vrd/maskrcnn_benchmark/__init__.py
mmkg_vrd/maskrcnn_benchmark/config/__init__.py
mmkg_vrd/maskrcnn_benchmark/config/defaults.py
mmkg_vrd/maskrcnn_benchmark/config/paths_catalog.py
mmkg_vrd/maskrcnn_benchmark/data/__init__.py
mmkg_vrd/maskrcnn_benchmark/data/build.py
mmkg_vrd/maskrcnn_benchmark/data/collate_batch.py
mmkg_vrd/maskrcnn_benchmark/data/datasets/__init__.py
mmkg_vrd/maskrcnn_benchmark/data/datasets/abstract.py
mmkg_vrd/maskrcnn_benchmark/data/datasets/cityscapes.py
mmkg_vrd/maskrcnn_benchmark/data/datasets/coco.py
mmkg_vrd/maskrcnn_benchmark/data/datasets/concat_dataset.py
mmkg_vrd/maskrcnn_benchmark/data/datasets/list_dataset.py
mmkg_vrd/maskrcnn_benchmark/data/datasets/od_tsv.py
mmkg_vrd/maskrcnn_benchmark/data/datasets/openimages_vrd_tsv.py
mmkg_vrd/maskrcnn_benchmark/data/datasets/relation_tsv.py
mmkg_vrd/maskrcnn_benchmark/data/datasets/tsv_dataset.py
mmkg_vrd/maskrcnn_benchmark/data/datasets/vg_tsv.py
mmkg_vrd/maskrcnn_benchmark/data/datasets/voc.py
mmkg_vrd/maskrcnn_benchmark/data/datasets/evaluation/__init__.py
mmkg_vrd/maskrcnn_benchmark/data/datasets/evaluation/utils.py
mmkg_vrd/maskrcnn_benchmark/data/datasets/evaluation/cityscapes/__init__.py
mmkg_vrd/maskrcnn_benchmark/data/datasets/evaluation/cityscapes/cityscapes_eval.py
mmkg_vrd/maskrcnn_benchmark/data/datasets/evaluation/cityscapes/eval_instances.py
mmkg_vrd/maskrcnn_benchmark/data/datasets/evaluation/coco/__init__.py
mmkg_vrd/maskrcnn_benchmark/data/datasets/evaluation/coco/abs_to_coco.py
mmkg_vrd/maskrcnn_benchmark/data/datasets/evaluation/coco/coco_eval.py
mmkg_vrd/maskrcnn_benchmark/data/datasets/evaluation/coco/coco_eval_wrapper.py
mmkg_vrd/maskrcnn_benchmark/data/datasets/evaluation/openimages_vrd/__init__.py
mmkg_vrd/maskrcnn_benchmark/data/datasets/evaluation/openimages_vrd/eval_utils.py
mmkg_vrd-0.2.0.dist-info/METADATA
mmkg_vrd-0.2.0.dist-info/WHEEL
mmkg_vrd-0.2.0.dist-info/top_level.txt
mmkg_vrd-0.2.0.dist-info/RECORD
